rqmonitor/__init__.py
rqmonitor/__main__.py
rqmonitor/bp.py
rqmonitor/cli.py
rqmonitor/constants.py
rqmonitor/decorators.py
rqmonitor/defaults.py
rqmonitor/exceptions.py
rqmonitor/utils.py
rqmonitor/version.py
rqmonitor/static/assets/images/redis.png
rqmonitor/static/assets/libs/css/style.css
rqmonitor/static/assets/libs/js/main-js.js
rqmonitor/static/assets/vendor/bootstrap/css/bootstrap.min.css
rqmonitor/static/assets/vendor/bootstrap/js/bootstrap.bundle.js
rqmonitor/static/assets/vendor/datatables/css/dataTables.bootstrap4.css
rqmonitor/static/assets/vendor/datatables/js/dataTables.bootstrap4.min.js
rqmonitor/static/assets/vendor/datatables/js/jquery.dataTables.min.js
rqmonitor/static/assets/vendor/fonts/circular-std/CircularStd-Black.woff
rqmonitor/static/assets/vendor/fonts/circular-std/CircularStd-BlackItalic.woff
rqmonitor/static/assets/vendor/fonts/circular-std/CircularStd-Bold.woff
rqmonitor/static/assets/vendor/fonts/circular-std/CircularStd-BoldItalic.woff
rqmonitor/static/assets/vendor/fonts/circular-std/CircularStd-Book.woff
rqmonitor/static/assets/vendor/fonts/circular-std/CircularStd-BookItalic.woff
rqmonitor/static/assets/vendor/fonts/circular-std/CircularStd-Medium.woff
rqmonitor/static/assets/vendor/fonts/circular-std/CircularStd-MediumItalic.woff
rqmonitor/static/assets/vendor/fonts/circular-std/style.css
rqmonitor/static/assets/vendor/fonts/fontawesome/css/fontawesome-all.css
rqmonitor/static/assets/vendor/fonts/fontawesome/webfonts/fa-brands-400.eot
rqmonitor/static/assets/vendor/fonts/fontawesome/webfonts/fa-brands-400.html
rqmonitor/static/assets/vendor/fonts/fontawesome/webfonts/fa-brands-400.svg
rqmonitor/static/assets/vendor/fonts/fontawesome/webfonts/fa-brands-400.ttf
rqmonitor/static/assets/vendor/fonts/fontawesome/webfonts/fa-brands-400.woff
rqmonitor/static/assets/vendor/fonts/fontawesome/webfonts/fa-brands-400d41d.eot
rqmonitor/static/assets/vendor/fonts/fontawesome/webfonts/fa-regular-400.eot
rqmonitor-1.0.6.dist-info/AUTHORS
rqmonitor-1.0.6.dist-info/LICENSE
rqmonitor-1.0.6.dist-info/METADATA
rqmonitor-1.0.6.dist-info/WHEEL
rqmonitor-1.0.6.dist-info/entry_points.txt
rqmonitor-1.0.6.dist-info/top_level.txt
rqmonitor-1.0.6.dist-info/RECORD
