Metadata-Version: 2.1
Name: rqmonitor
Version: 1.0.6
Summary: Flask based dynamic and actionable dashboard for monitoring RQs
Home-page: https://github.com/pranavgupta1234/rqmonitor
Author: Pranav Gupta
Author-email: pranavgupta4321@gmail.com
License: Apache Software License
Download-URL: https://github.com/pranavgupta1234/rqmonitor/archive/v_1.0.6.tar.gz
Platform: any
Classifier: Intended Audience :: Developers
Classifier: Topic :: Software Development :: Build Tools
Classifier: License :: OSI Approved :: Apache Software License
Classifier: Programming Language :: Python :: 3.5
Classifier: Programming Language :: Python :: 3.6
Classifier: Programming Language :: Python :: 3.7
Classifier: Programming Language :: Python :: 3.8
Requires-Dist: redis (>=3.3.11)
Requires-Dist: humanize (>=2.4.0)
Requires-Dist: Flask (>=1.1.1)
Requires-Dist: Click (>=7.0)
Requires-Dist: six (>=1.13.0)
Requires-Dist: Werkzeug (>=0.16.0)
Requires-Dist: rq (>=1.4.0)
Requires-Dist: fabric (>=2.5.0)
Requires-Dist: invoke (>=1.4.1)
